pipruncommon/__init__.py
pipruncommon/component.py
pipruncommon/constants.py
pipruncommon/db_setup.py
pipruncommon/graph.py
pipruncommon/index_entities_request.py
pipruncommon/input_output.py
piprundb/__init__.py
piprundb/all_tables.py
piprundb/component_metadata.py
piprundb/db_query.py
piprundb/experiment_metadata.py
piprundb/run_definition.py
piprundb/run_history.py
piprundebug/__init__.py
piprundebug/base_debugger.py
piprundebug/debug_meta.py
piprundebug/debug_util.py
piprundebug/devcontainer_properties.py
piprundebug/py_debugger.py
piprundebug/r_debugger.py
piprundebug/language/R/Dockerfile
piprundebug/language/R/launch.json
piprundebug/language/python/Dockerfile
piprundebug/language/python/launch.json
piprunengine/__init__.py
piprunengine/_utils.py
piprunengine/constants.py
piprunengine/dockerfile_resolver.py
piprunengine/environment_resolver.py
piprunengine/executor.py
piprunengine/graph.py
piprunengine/image_builder.py
piprunengine/logger.py
piprunengine/metadata.py
pipelinelocalrun-0.2.0.dist-info/LICENSE
pipelinelocalrun-0.2.0.dist-info/METADATA
pipelinelocalrun-0.2.0.dist-info/WHEEL
pipelinelocalrun-0.2.0.dist-info/top_level.txt
pipelinelocalrun-0.2.0.dist-info/RECORD
