Metadata-Version: 2.1
Name: pipelinelocalrun
Version: 0.2.0
Summary: Package to support pipeline local run
Home-page: https://github.com/Azure/aml_pipeline_local_run
Author: Xiaopeng Wang
Author-email: xiaopwan@microsoft.com
Classifier: Programming Language :: Python :: 3
Classifier: License :: OSI Approved :: MIT License
Classifier: Operating System :: OS Independent
Requires-Python: >=3.7
License-File: LICENSE
Requires-Dist: docker
Requires-Dist: SQLAlchemy (<2.0.0,>=1.4.38)
Requires-Dist: jsonpickle (>=2.2.0)
Requires-Dist: azure-ai-ml (>=1.1.0)
Requires-Dist: mldesigner (>=0.1.0b8)
Requires-Dist: jsonpatch (>=1.32)
